{
  "date": "2025-12-26",
  "idiom": {
    "characters": "风吹草动",
    "pinyin": "fēng chuī cǎo dòng",
    "meaning": "React to slightest hint of change or activity",
    "example": "The military command analyzed every minor border incident for signs of potential conflict",
    "theme": "Life Philosophy"
  },
  "shortDescription": "Tang Dynasty military scouts first used this phrase to describe how wind (风) blowing (吹) causes grass (草) to move (动), revealing subtle signs of enemy movement. Song Dynasty officials expanded it to describe political sensitivity to small social changes. The environmental metapho...",
  "hashtags": [
    "ChineseIdioms",
    "LearnChinese",
    "ChineseCulture",
    "LifePhilosophy"
  ]
}